bifsg/__init__.py
bifsg/core.py
bifsg/data_prep.py
bifsg/data/.gitkeep
bifsg/data/Names_2010Census.xlsx
bifsg/data/__init__.py
bifsg/data/firstnames.xlsx
bifsg/data/firstnames_updated.parquet
bifsg/data/nat_population.yaml
bifsg/data/surnames_updated.parquet
bifsg-0.1.1.dist-info/licenses/LICENSE
bifsg-0.1.1.dist-info/METADATA
bifsg-0.1.1.dist-info/WHEEL
bifsg-0.1.1.dist-info/entry_points.txt
bifsg-0.1.1.dist-info/top_level.txt
bifsg-0.1.1.dist-info/RECORD
