Metadata-Version: 2.4
Name: bifsg
Version: 0.1.1
Summary: Bayesian Improved First-Firstname Surname Geocoding
Author-email: Ningxin Huang <huangningxin@gmail.com>
License: MIT
Requires-Python: >=3.7
License-File: LICENSE
Requires-Dist: requests>=2.0
Requires-Dist: PyYAML
Requires-Dist: pandas>=1.0
Requires-Dist: numpy
Requires-Dist: pyarrow
Requires-Dist: openpyxl
Dynamic: license-file
